README.md
setup.py
test/__init__.py
test/test_all_of_complete_correction_request_sentence_keyboard.py
test/test_all_of_complete_correction_request_sentence_language.py
test/test_all_of_completion_request_language.py
test/test_all_of_last_word_correction_request_sentence_keyboard.py
test/test_all_of_last_word_correction_request_sentence_language.py
test/test_complete_correction_reply.py
test/test_complete_correction_request_sentence.py
test/test_completion_api.py
test/test_completion_reply.py
test/test_completion_request.py
test/test_correction_api.py
test/test_default_api.py
test/test_emoji_api.py
test/test_emoji_search_reply.py
test/test_emoji_search_request.py
test/test_http_validation_error.py
test/test_keyboard.py
test/test_language_detection_api.py
test/test_language_detection_reply.py
test/test_language_detection_request.py
test/test_last_word_correction_reply.py
test/test_last_word_correction_request_sentence.py
test/test_server_routes_completion_pydantic_models_language.py
test/test_server_routes_correction_pydantic_models_language.py
test/test_server_routes_language_detection_pydantic_models_language.py
test/test_single_completion.py
test/test_single_completion_token_probability.py
test/test_single_language_prediction.py
test/test_single_point_correction.py
test/test_validation_error.py
typewiseprediction/__init__.py
typewiseprediction/api_client.py
typewiseprediction/configuration.py
typewiseprediction/rest.py
typewiseprediction.egg-info/PKG-INFO
typewiseprediction.egg-info/SOURCES.txt
typewiseprediction.egg-info/dependency_links.txt
typewiseprediction.egg-info/requires.txt
typewiseprediction.egg-info/top_level.txt
typewiseprediction/api/__init__.py
typewiseprediction/api/completion_api.py
typewiseprediction/api/correction_api.py
typewiseprediction/api/default_api.py
typewiseprediction/api/emoji_api.py
typewiseprediction/api/language_detection_api.py
typewiseprediction/models/__init__.py
typewiseprediction/models/all_of_complete_correction_request_sentence_keyboard.py
typewiseprediction/models/all_of_complete_correction_request_sentence_language.py
typewiseprediction/models/all_of_completion_request_language.py
