Metadata-Version: 1.0
Name: typewiseprediction
Version: 1.0.0
Summary: Typewise API
Home-page: UNKNOWN
Author: UNKNOWN
Author-email: UNKNOWN
License: UNKNOWN
Keywords: Swagger,Typewise API
Platform: UNKNOWN
